{
	"class" : {
		"delete:" : "SvenVanCaekenberghe 3/4/2012 10:20",
		"delete:username:password:" : "SvenVanCaekenberghe 3/4/2012 10:21",
		"get:" : "SvenVanCaekenberghe 3/4/2012 10:21",
		"get:username:password:" : "SvenVanCaekenberghe 3/4/2012 10:21",
		"getGif:" : "SvenVanCaekenberghe 3/4/2012 10:21",
		"getJpeg:" : "SvenVanCaekenberghe 3/4/2012 10:21",
		"getPng:" : "SvenVanCaekenberghe 3/4/2012 10:21",
		"head:" : "SvenVanCaekenberghe 3/4/2012 10:21",
		"head:username:password:" : "SvenVanCaekenberghe 3/4/2012 10:21",
		"post:data:" : "SvenVanCaekenberghe 3/4/2012 10:21",
		"post:data:username:password:" : "SvenVanCaekenberghe 3/4/2012 10:21",
		"put:data:" : "SvenVanCaekenberghe 3/4/2012 10:21",
		"put:data:username:password:" : "SvenVanCaekenberghe 3/4/2012 10:21" },
	"instance" : {
		 } }
